PTansformer/__init__.py
PTansformer/dataset.py
PTansformer/model.py
PTransformer-0.0.1.2.dist-info/METADATA
PTransformer-0.0.1.2.dist-info/WHEEL
PTransformer-0.0.1.2.dist-info/top_level.txt
PTransformer-0.0.1.2.dist-info/RECORD
