Metadata-Version: 2.1
Name: PTransformer
Version: 0.0.1.2
Summary: This is Ai Transformer
Author: ProgramerSalar
Author-email: <manishkumar60708090@gmail.com>
Keywords: python,transformer,chat-GPT Transformer
Classifier: Development Status :: 1 - Planning
Classifier: Intended Audience :: Developers
Classifier: Programming Language :: Python :: 3
Classifier: Operating System :: Unix
Classifier: Operating System :: MacOS :: MacOS X
Classifier: Operating System :: Microsoft :: Windows
Requires-Dist: torch
